docs/conf.py
pyrca/__init__.py
pyrca/base.py
pyrca/analyzers/__init__.py
pyrca/analyzers/base.py
pyrca/analyzers/bayesian.py
pyrca/analyzers/epsilon_diagnosis.py
pyrca/analyzers/ht.py
pyrca/analyzers/random_walk.py
pyrca/analyzers/rcd.py
pyrca/applications/example/dataset.py
pyrca/applications/example/rca.py
pyrca/graphs/__init__.py
pyrca/graphs/causal/__init__.py
pyrca/graphs/causal/base.py
pyrca/graphs/causal/fges.py
pyrca/graphs/causal/ges.py
pyrca/graphs/causal/lingam.py
pyrca/graphs/causal/pc.py
pyrca/outliers/__init__.py
pyrca/outliers/base.py
pyrca/outliers/stats.py
pyrca/simulation/__init__.py
pyrca/simulation/data_gen.py
pyrca/thirdparty/__init__.py
pyrca/thirdparty/causallearn/graph/AdjacencyConfusion.py
pyrca/thirdparty/causallearn/graph/ArrowConfusion.py
pyrca/thirdparty/causallearn/graph/Dag.py
pyrca/thirdparty/causallearn/graph/Edge.py
pyrca/thirdparty/causallearn/graph/Edges.py
pyrca/thirdparty/causallearn/graph/Endpoint.py
pyrca/thirdparty/causallearn/graph/GeneralGraph.py
pyrca/thirdparty/causallearn/graph/Graph.py
pyrca/thirdparty/causallearn/graph/GraphClass.py
pyrca/thirdparty/causallearn/graph/GraphNode.py
pyrca/thirdparty/causallearn/graph/Node.py
pyrca/thirdparty/causallearn/graph/NodeType.py
pyrca/thirdparty/causallearn/graph/NodeVariableType.py
pyrca/thirdparty/causallearn/graph/SHD.py
pyrca/thirdparty/causallearn/score/LocalScoreFunction.py
pyrca/thirdparty/causallearn/score/LocalScoreFunctionClass.py
pyrca/thirdparty/causallearn/search/ConstraintBased/PC.py
pyrca/thirdparty/causallearn/search/ScoreBased/GES.py
pyrca/thirdparty/causallearn/utils/BackgroundKnowledge.py
pyrca/thirdparty/causallearn/utils/DAG2CPDAG.py
pyrca/thirdparty/causallearn/utils/GESUtils.py
pyrca/thirdparty/causallearn/utils/GraphUtils.py
pyrca/thirdparty/causallearn/utils/PDAG2DAG.py
pyrca/thirdparty/causallearn/utils/ScoreUtils.py
pyrca/thirdparty/causallearn/utils/TXT2GeneralGraph.py
pyrca/thirdparty/causallearn/utils/cit.py
sfr_pyrca-1.0.1.dist-info/LICENSE
sfr_pyrca-1.0.1.dist-info/METADATA
sfr_pyrca-1.0.1.dist-info/WHEEL
sfr_pyrca-1.0.1.dist-info/top_level.txt
sfr_pyrca-1.0.1.dist-info/RECORD
