Metadata-Version: 2.1
Name: sfr-pyrca
Version: 1.0.1
Summary: PyRCA: A Python library for Root Cause Analysis
Home-page: https://github.com/salesforce/PyRCA
Author: Salesforce Research Warden AIOps
License: 3-Clause BSD
Keywords: AIOps RCA root cause analysis
Requires-Python: >=3.7,<4
License-File: LICENSE
Requires-Dist: numpy (>=1.17)
Requires-Dist: pandas (>=1.1.0)
Requires-Dist: scikit-learn (<1.2,>=0.24)
Requires-Dist: networkx (>=2.6)
Requires-Dist: matplotlib
Requires-Dist: pyyaml
Requires-Dist: schema
Requires-Dist: pyparsing
Requires-Dist: dill
Requires-Dist: tqdm
Requires-Dist: wheel
Requires-Dist: packaging
Requires-Dist: javabridge (>=1.0.11)
Provides-Extra: all
Requires-Dist: plotly (>=4) ; extra == 'all'
Requires-Dist: dash (>=2.0) ; extra == 'all'
Requires-Dist: dash-bootstrap-components (>=1.0) ; extra == 'all'
Requires-Dist: jupyter-dash (>=0.4) ; extra == 'all'
Requires-Dist: dash[diskcache] ; extra == 'all'
Requires-Dist: dash-cytoscape ; extra == 'all'
Provides-Extra: plot
Requires-Dist: plotly (>=4) ; extra == 'plot'
Requires-Dist: dash (>=2.0) ; extra == 'plot'
Requires-Dist: dash-bootstrap-components (>=1.0) ; extra == 'plot'
Requires-Dist: jupyter-dash (>=0.4) ; extra == 'plot'
Requires-Dist: dash[diskcache] ; extra == 'plot'
Requires-Dist: dash-cytoscape ; extra == 'plot'
